smart_round/__init__.py
smart_round-1.0.1.dist-info/licenses/LICENSE
smart_round-1.0.1.dist-info/METADATA
smart_round-1.0.1.dist-info/WHEEL
smart_round-1.0.1.dist-info/top_level.txt
smart_round-1.0.1.dist-info/RECORD
