Metadata-Version: 2.4
Name: smart_round
Version: 1.0.1
Summary: Intelligent value rounding and formatting for better numeric readability
Author-email: Kirill Nikolsky <kirill.s.nikolsky@yandex.ru>
License: MIT
Project-URL: Homepage, https://github.com/protdb/smart_round
Project-URL: Bug Tracker, https://github.com/protdb/smart_round/issues
Classifier: Programming Language :: Python :: 3
Classifier: Programming Language :: Python :: 3.7
Classifier: Programming Language :: Python :: 3.8
Classifier: Programming Language :: Python :: 3.9
Classifier: Programming Language :: Python :: 3.10
Classifier: License :: OSI Approved :: MIT License
Classifier: Operating System :: OS Independent
Classifier: Intended Audience :: Developers
Classifier: Intended Audience :: Science/Research
Classifier: Topic :: Scientific/Engineering :: Mathematics
Classifier: Topic :: Software Development :: Libraries :: Python Modules
Requires-Python: >=3.7
License-File: LICENSE
Provides-Extra: numpy
Requires-Dist: numpy>=1.19.0; extra == "numpy"
Provides-Extra: pandas
Requires-Dist: pandas>=1.0.0; extra == "pandas"
Requires-Dist: numpy>=1.19.0; extra == "pandas"
Provides-Extra: all
Requires-Dist: numpy>=1.19.0; extra == "all"
Requires-Dist: pandas>=1.0.0; extra == "all"
Dynamic: license-file
